pytfiac.py
pytfiac-0.4.dist-info/LICENSE
pytfiac-0.4.dist-info/METADATA
pytfiac-0.4.dist-info/WHEEL
pytfiac-0.4.dist-info/top_level.txt
pytfiac-0.4.dist-info/RECORD
